eboekhoudenapi/__init__.py
eboekhoudenapi/client.py
eboekhoudenapi/models/__init__.py
eboekhoudenapi/models/mutatie.py
eboekhoudenapi/models/mutatie_regel.py
tests/__init__.py
tests/test_client.py
eboekhoudenapi-1.4.0.dist-info/METADATA
eboekhoudenapi-1.4.0.dist-info/WHEEL
eboekhoudenapi-1.4.0.dist-info/top_level.txt
eboekhoudenapi-1.4.0.dist-info/RECORD
