Metadata-Version: 2.1
Name: eboekhoudenapi
Version: 1.4.0
Summary: EBoekhouden API
Home-page: UNKNOWN
Author-email: info@inogo.nl
License: UNKNOWN
Keywords: Soap,EBoekhouden API
Platform: UNKNOWN
Requires-Dist: certifi (>=2017.4.17)
Requires-Dist: python-dateutil (>=2.1)
Requires-Dist: six (>=1.10)
Requires-Dist: urllib3 (>=1.23)
